src/location_properties_pkg/LocationHandler.py
src/location_properties_pkg/__init__.py
example_package_erel_ozturk-0.0.1.dist-info/METADATA
example_package_erel_ozturk-0.0.1.dist-info/WHEEL
example_package_erel_ozturk-0.0.1.dist-info/licenses/LICENSE
example_package_erel_ozturk-0.0.1.dist-info/RECORD
